pandatorch/__init__.py
pandatorch/data.py
pandatorch/model.py
pandatorch-2.1.0.dist-info/WHEEL
pandatorch-2.1.0.dist-info/METADATA
pandatorch-2.1.0.dist-info/RECORD
