Metadata-Version: 2.1
Name: pandatorch
Version: 2.1.0
Summary: A flexible simple library that makes it easier to use the extrememly popular pandas package with the other extremely popular framework PyTorch. 
License: MIT
Author: Ashwin Iyer
Author-email: ashwiniyer1706@gmail.com
Requires-Python: >=3.9,<4.0
Classifier: License :: OSI Approved :: MIT License
Classifier: Programming Language :: Python :: 3
Classifier: Programming Language :: Python :: 3.10
Classifier: Programming Language :: Python :: 3.9
Requires-Dist: matplotlib (>=3.5.1,<4.0.0)
Requires-Dist: pandas (>=1.4.1,<2.0.0)
